Metadata-Version: 2.1
Name: turbo-burbo-generator111
Version: 0.0.1
Summary: My Package
Author: Your Name
Author-email: suhomlinbi@gmail.com
